vending_machine.srcs/sources_1/new/fsm_enhanced.v
module fsm_enhanced(
    input clk,
    input rst,
    input one, two, five,
    input select, 
    output reg dispense_tea,
    output reg dispense_coffee,
    output reg [3:0] change
);
    reg [3:0] balance; 

    always @(posedge clk or posedge rst) begin
        if (rst) begin
            balance <= 0;
            dispense_tea <= 0;
            dispense_coffee <= 0;
            change <= 0;
        end else begin
            dispense_tea <= 0;
            dispense_coffee <= 0;
            change <= 0;

            if (one) balance <= balance + 1;
            else if (two) balance <= balance + 2;
            else if (five) balance <= balance + 5;

            if (select == 0 && balance >= 5) begin
                dispense_tea <= 1;
                change <= balance - 5;
                balance <= 0;
            end else if (select == 1 && balance >= 7) begin
                dispense_coffee <= 1;
                change <= balance - 7;
                balance <= 0;
            end
        end
    end
endmodule

vending_machine.srcs/sim_1/new/tb2.v
module tb2;
    reg clk = 0;
    reg rst = 1;
    reg one = 0, two = 0, five = 0;
    reg select = 0;
    wire dispense_tea, dispense_coffee;
    wire [3:0] change;

    fsm_enhanced  uut (
        .clk(clk), .rst(rst),
        .one(one), .two(two), .five(five),
        .select(select),
        .dispense_tea(dispense_tea),
        .dispense_coffee(dispense_coffee),
        .change(change)
    );

    always #5 clk = ~clk;

    initial begin
        $dumpfile("enhanced_vending.vcd");
        $dumpvars(0, tb2);

        #10 rst = 0;

       
        select = 0;
        #10 two = 1; #10 two = 0;
        #10 two = 1; #10 two = 0;
        #10 one = 1; 
        #10 one = 0;
        #10 two = 1; #10 two =0;
        #50;

       
        select = 1;
        #10 five = 1; #10 five = 0;
        #10 one = 1; # 10 one =0;
        #10 two = 1; #10 two = 0;
        #20;

        select = 1;
        #10 five = 1; #10 five = 0;
        #10 five = 1; #10 five = 0;
        #20;

        $finish;
    end
endmodule

vending_machine.sim/sim_1/behav/xsim/enhanced_vending.vcd
$date
   Tue Jul 15 19:48:47 2025
$end
$version
  2018.2
$end
$timescale
  1ps
$end
$scope module tb2 $end
$var reg 1 ! clk $end
$var reg 1 " rst $end
$var reg 1 # one $end
$var reg 1 $ two $end
$var reg 1 % five $end
$var reg 1 & select $end
$var wire 1 ' dispense_tea $end
$var wire 1 ( dispense_coffee $end
$var wire 4 ) change [3:0] $end
$scope module uut $end
$var wire 1 * clk $end
$var wire 1 + rst $end
$var wire 1 , one $end
$var wire 1 - two $end
$var wire 1 . five $end
$var wire 1 / select $end
$var reg 1 0 dispense_tea $end
$var reg 1 1 dispense_coffee $end
$var reg 4 2 change [3:0] $end
$var reg 4 3 balance [3:0] $end
$upscope $end
$upscope $end
$enddefinitions $end
#0
$dumpvars
0!
1"
0#
0$
0%
0&
0'
0(
b0 )
0*
1+
0,
0-
0.
0/
00
01
b0 2
b0 3
$end
#5000
1!
1*
#10000
0!
0"
0*
0+
#15000
1!
1*
#20000
0!
1$
0*
1-
#25000
1!
1*
b10 3
#30000
0!
0$
0*
0-
#35000
1!
1*
#40000
0!
1$
0*
1-
#45000
1!
1*
b100 3
#50000
0!
0$
0*
0-
#55000
1!
1*
#60000
0!
1#
0*
1,
#65000
1!
1*
b101 3
#70000
0!
0#
0*
0,
#75000
1!
1'
1*
10
b0 3
#80000
0!
1$
0*
1-
#85000
1!
0'
1*
00
b10 3
#90000
0!
0$
0*
0-
#95000
1!
1*
#100000
0!
0*
#105000
1!
1*
#110000
0!
0*
#115000
1!
1*
#120000
0!
0*
#125000
1!
1*
#130000
0!
0*
#135000
1!
1*
#140000
0!
1&
0*
1/
#145000
1!
1*
#150000
0!
1%
0*
1.
#155000
1!
1*
b111 3
#160000
0!
0%
0*
0.
#165000
1!
1(
1*
11
b0 3
#170000
0!
1#
0*
1,
#175000
1!
0(
1*
01
b1 3
#180000
0!
0#
0*
0,
#185000
1!
1*
#190000
0!
1$
0*
1-
#195000
1!
1*
b11 3
#200000
0!
0$
0*
0-
#205000
1!
1*
#210000
0!
0*
#215000
1!
1*
#220000
0!
0*
#225000
1!
1*
#230000
0!
1%
0*
1.
#235000
1!
1*
b1000 3
#240000
0!
0%
0*
0.
#245000
1!
1(
b1 )
1*
11
b1 2
b0 3
#250000
0!
1%
0*
1.
#255000
1!
0(
b0 )
1*
01
b0 2
b101 3
#260000
0!
0%
0*
0.
