vending_machine.srcs/sources_1/new/fsm_basic.v
module fsm_basic(
    input clk,
    input rst,
    input one,       
    input two,      
    output reg dispense,
    output reg [2:0] change
);

    reg [2:0] state;

    parameter S0=3'd0, S1=3'd1, S2=3'd2, S3=3'd3, S4=3'd4, S5=3'd5;

    always @(posedge clk or posedge rst) begin
        if (rst) begin
            state <= S0;
            dispense <= 0;
            change <= 0;
        end else begin
            dispense <= 0;
            change <= 0;
            case (state)
                S0: if (one) state <= S1; else if (two) state <= S2;
                S1: if (one) state <= S2; else if (two) state <= S3;
                S2: if (one) state <= S3; else if (two) state <= S4;
                S3: if (one) state <= S4; else if (two) state <= S5;
                S4: if (one) state <= S5;
                    else if (two) begin state <= S5; change <= 1; end
                S5: begin
                    dispense <= 1;
                    state <= S0;
                    change <= 0;
                end
            endcase
        end
    end
endmodule

vending_machine.srcs/sim_1/new/tb1.v
`timescale 1ns / 1ps
    module tb1;
    reg clk = 0;
    reg rst = 1;
    reg one = 0, two = 0;
    wire dispense;
    wire [2:0] change;

   fsm_basic uut (.clk(clk), .rst(rst), .one(one), .two(two), .dispense(dispense), .change(change));

    always #5 clk = ~clk;

    initial begin
        $dumpfile("vending.vcd");
        $dumpvars(0, tb1);
        #10 rst = 0;
        #10 two = 1; #10 two = 0;       
        #10 two = 1; #10 two = 0;       
        #10 two = 1; #10 two = 0;       
        #10 one = 1; #10 one = 0;       
        #10 one = 1; #10 one = 0;       
        #40;

        $finish;
    end
endmodule

vending_machine.sim/sim_1/behav/xsim/vending.vcd
$date
   Tue Jul 15 17:29:46 2025
$end
$version
  2018.2
$end
$timescale
  1ps
$end
$scope module tb1 $end
$var reg 1 ! clk $end
$var reg 1 " rst $end
$var reg 1 # one $end
$var reg 1 $ two $end
$var wire 1 % dispense $end
$var wire 3 & change [2:0] $end
$scope module uut $end
$var wire 1 ' clk $end
$var wire 1 ( rst $end
$var wire 1 ) one $end
$var wire 1 * two $end
$var reg 1 + dispense $end
$var reg 3 , change [2:0] $end
$var reg 3 - state [2:0] $end
$var parameter 3 . S0 [2:0] $end
$var parameter 3 / S1 [2:0] $end
$var parameter 3 0 S2 [2:0] $end
$var parameter 3 1 S3 [2:0] $end
$var parameter 3 2 S4 [2:0] $end
$var parameter 3 3 S5 [2:0] $end
$upscope $end
$upscope $end
$enddefinitions $end
#0
$dumpvars
0!
1"
0#
0$
0%
b0 &
0'
1(
0)
0*
0+
b0 ,
b0 -
b0 .
b1 /
b10 0
b11 1
b100 2
b101 3
$end
#5000
1!
1'
#10000
0!
0"
0'
0(
#15000
1!
1'
#20000
0!
1$
0'
1*
#25000
1!
1'
b10 -
#30000
0!
0$
0'
0*
#35000
1!
1'
#40000
0!
1$
0'
1*
#45000
1!
1'
b100 -
#50000
0!
0$
0'
0*
#55000
1!
1'
#60000
0!
1$
0'
1*
#65000
1!
b1 &
1'
b1 ,
b101 -
#70000
0!
0$
0'
0*
#75000
1!
1%
b0 &
1'
1+
b0 ,
b0 -
#80000
0!
1#
0'
1)
#85000
1!
0%
1'
0+
b1 -
#90000
0!
0#
0'
0)
#95000
1!
1'
#100000
0!
1#
0'
1)
#105000
1!
1'
b10 -
#110000
0!
0#
0'
0)
